{
  "body": "",
  "contributors": "[{\"Contributor\":\"Larrotiz\",\"Payout Address\":\"0x5640Ddc028f2436B5C0BA0305D2199556C1b5a95\",\"Voting Address\":\"\",\"Eth\":\"0\",\"Mooney\":\"0\",\"Dai\":\"1,718.95\"},{\"Contributor\":\"pmoncada\",\"Payout Address\":\"0x679d87D8640e66778c3419D164998E720D7495f6\",\"Voting Address\":\"\",\"Eth\":\"0\",\"Mooney\":\"175,708\",\"Dai\":\"2,000.00\"},{\"Contributor\":\"Manuel\",\"Payout Address\":\"0xE862E2C1ca94eAcfEDe3c95a217c15EF0086a29D\",\"Voting Address\":\"\",\"Eth\":\"0\",\"Mooney\":\"251,088\",\"Dai\":\"2,312.61\"},{\"Contributor\":\"JustinPark01\",\"Payout Address\":\"0x9A1741b58Bd99EBbc4e9742Bd081b887DfC95f53\",\"Voting Address\":\"\",\"Eth\":\"0\",\"Mooney\":\"41,533\",\"Dai\":\"1,000.00\"}]"
}
